SIOTC/DatabaseLayer.py
SIOTC/Operations.py
SIOTC/__init__.py
SIOTC/helperhttps.py
SIOTCommon-0.1.5.dist-info/METADATA
SIOTCommon-0.1.5.dist-info/WHEEL
SIOTCommon-0.1.5.dist-info/top_level.txt
SIOTCommon-0.1.5.dist-info/RECORD
