Metadata-Version: 2.1
Name: SIOTCommon
Version: 0.1.5
Summary: Common operations for sweiot microservices
Home-page: https://github.com/AntonNPersson/SweIoTServices.git
Author: Anton Persson
Author-email: Antonnilspersson@gmail.com
Classifier: Programming Language :: Python :: 3.10
Classifier: Operating System :: OS Independent
Requires-Dist: bleach (==6.0.0)
Requires-Dist: certifi (==2022.12.7)
Requires-Dist: charset-normalizer (==3.1.0)
Requires-Dist: click (==8.1.3)
Requires-Dist: colorama (==0.4.6)
Requires-Dist: docutils (==0.19)
Requires-Dist: Flask (==2.2.3)
Requires-Dist: Flask-JWT-Extended (==4.4.4)
Requires-Dist: greenlet (==2.0.2)
Requires-Dist: idna (==3.4)
Requires-Dist: importlib-metadata (==6.3.0)
Requires-Dist: itsdangerous (==2.1.2)
Requires-Dist: jaraco.classes (==3.2.3)
Requires-Dist: Jinja2 (==3.1.2)
Requires-Dist: keyring (==23.13.1)
Requires-Dist: markdown-it-py (==2.2.0)
Requires-Dist: MarkupSafe (==2.1.2)
Requires-Dist: mdurl (==0.1.2)
Requires-Dist: more-itertools (==9.1.0)
Requires-Dist: pkginfo (==1.9.6)
Requires-Dist: Pygments (==2.15.0)
Requires-Dist: PyJWT (==2.6.0)
Requires-Dist: pywin32-ctypes (==0.2.0)
Requires-Dist: readme-renderer (==37.3)
Requires-Dist: requests (==2.28.2)
Requires-Dist: requests-toolbelt (==0.10.1)
Requires-Dist: rfc3986 (==2.0.0)
Requires-Dist: rich (==13.3.3)
Requires-Dist: six (==1.16.0)
Requires-Dist: SQLAlchemy (==2.0.9)
Requires-Dist: twine (==4.0.2)
Requires-Dist: typing-extensions (==4.5.0)
Requires-Dist: urllib3 (==1.26.15)
Requires-Dist: webencodings (==0.5.1)
Requires-Dist: Werkzeug (==2.2.3)
Requires-Dist: zipp (==3.15.0)
